{
  "$defs": {
    "StatModifiers": {
      "additionalProperties": false,
      "properties": {
        "maxHp": {
          "default": 0,
          "format": "int32",
          "type": "integer"
        }
      },
      "type": "object"
    }
  },
  "$id": "https://raw.githubusercontent.com/UncleFvcker/RoguelikeFansBand-Rewrite/main/schemas/content-v1/item.schema.json",
  "$schema": "https://json-schema.org/draft/2020-12/schema",
  "additionalProperties": false,
  "properties": {
    "$schema": {
      "type": "string"
    },
    "descriptionKey": {
      "type": "string"
    },
    "equipmentSlot": {
      "default": null,
      "type": [
        "string",
        "null"
      ]
    },
    "formatVersion": {
      "format": "uint16",
      "maximum": 65535,
      "minimum": 0,
      "type": "integer"
    },
    "glyph": {
      "type": "string"
    },
    "id": {
      "type": "string"
    },
    "maxStack": {
      "format": "uint32",
      "minimum": 0,
      "type": "integer"
    },
    "modifiers": {
      "$ref": "#/$defs/StatModifiers",
      "default": {
        "maxHp": 0
      }
    },
    "nameKey": {
      "type": "string"
    },
    "tags": {
      "items": {
        "type": "string"
      },
      "type": "array"
    }
  },
  "required": [
    "$schema",
    "formatVersion",
    "id",
    "nameKey",
    "descriptionKey",
    "glyph",
    "maxStack",
    "tags"
  ],
  "title": "ItemDefinition",
  "type": "object"
}
